chembench/__init__.py
chembench/analysis.py
chembench/baseline.py
chembench/constant.py
chembench/evaluate.py
chembench/extractor.py
chembench/helper.py
chembench/metrics.py
chembench/model.py
chembench/prompter.py
chembench/refusal.py
chembench/report.py
chembench/task.py
chembench/types.py
chembench/utils.py
chembench/watermark.py
chembench-0.3.0.dist-info/LICENSE
chembench-0.3.0.dist-info/METADATA
chembench-0.3.0.dist-info/WHEEL
chembench-0.3.0.dist-info/entry_points.txt
chembench-0.3.0.dist-info/top_level.txt
chembench-0.3.0.dist-info/RECORD
